{"article_title": "Barack Obama\u2019s 12 Most Impressive Accomplishments In Office", "article_keywords": ["12", "impressive", "office", "barack", "accomplishments", "obamas"], "article_url": "http://www.newnownext.com/barack-obamas-12-most-impressive-accomplishments-in-office/01/2016/", "article_text": "", "article_metadata": {"description": "A look back at President Obama's most impressive accomplishments throughout his presidency.", "og": {"site_name": "LOGO News", "description": "From changing healthcare to trans rights.", "title": "Barack Obama\u2019s 12 Most Impressive Accomplishments In Office", "url": "http://www.newnownext.com/barack-obamas-12-most-impressive-accomplishments-in-office/01/2016/", "image": {"width": 1440, "identifier": "http://logoonline.mtvnimages.com/uri/mgid:uma:image:logotv.com:11259641?quality=0.8&format=jpg&width=1440&height=810&.jpg", "height": 810}, "type": "article"}, "twitter": {"url": "http://www.newnownext.com/barack-obamas-12-most-impressive-accomplishments-in-office/01/2016/", "image": "http://logoonline.mtvnimages.com/uri/mgid:uma:image:logotv.com:11259641?quality=0.8&format=jpg&width=500&height=375", "description": "A look back at President Obama's most impressive accomplishments throughout his presidency.", "card": "summary_large_image", "title": "Barack Obama\u2019s 12 Most Impressive Accomplishments In Office"}, "sm4": {"category": "News Articles - Life News", "parent": "mgid:wordpress:siteloc:www.newnownext.com:hp", "pubdate": "2016-01-25 6:09:44 PM +0000", "creator": "20D502000002D52000010002D520", "author": "Steve Philips", "alias": "post", "mgid": "mgid:wordpress:post:www.newnownext.com:409012", "type": "post"}, "fb": {"admins": "unset", "app_id": "unset"}, "ao": {"mgid": "mgid:wordpress:post:www.newnownext.com:409012"}, "HandheldFriendly": "True", "MobileOptimized": 320, "MTVNVevoHelper": {"beacon": "D4F4BE78-454E-44C3-B142-F9D269B9303E"}, "thumbnail": "http://logoonline.mtvnimages.com/uri/mgid:file:http:shared:newnownext.com/wp-content/uploads/2016/01/GettyImages-504725248-1453745470-300x197.jpg?quality=0.8&format=jpg", "viewport": "width=device-width, initial-scale=1, maximum-scale=1, user-scalable=0"}, "article_summary": ""}