{"article_title": "Here is the trailer for \u201cDumb and Dumber To\u201d", "article_keywords": ["dumber", "jeff", "daniels", "jim", "dumb", "lloyd", "harry", "yes", "comedy", "carrey", "trailer"], "article_url": "http://www.salon.com/2014/06/11/here_is_the_trailer_for_dumb_and_dumber_to/", "article_text": "Topics: aol_on, Comedy, Dumb and Dumber, dumb and dumber to, jeff daniels, Jim Carrey, Video, Entertainment News\n\nWatch the \u201cphe-nom-en-on\u201d that is Harry and Lloyd, reunited two decades later for \u201cDumb and Dumber To.\u201d Actors Jim Carrey and Jeff Daniels premiered the trailer for the sequel to their cult comedy classic on \u201cThe Tonight Show\u201d Tuesday night and, yes, the duo is still very dumb. Turns out that Harry still lives in the same apartment, has a cat named Butthole, but now he has an adult daughter (and Lloyd, not so surprisingly, wants to date her).\n\nBrace yourselves for lots of poop jokes (probably), bad haircuts (definitely), and general raunchiness. The movie comes out Nov. 14.", "article_metadata": {"description": "Jim Carrey and Jeff Daniels tease the movie as a \"phe-nom-en-on\" VIDEO", "author": "Prachi Gupta", "og": {"site_name": "Salon", "description": "Jim Carrey and Jeff Daniels tease the movie as a \"phe-nom-en-on\" VIDEO", "title": "Here is the trailer for \u201cDumb and Dumber To\u201d", "url": "http://www.salon.com/2014/06/11/here_is_the_trailer_for_dumb_and_dumber_to/", "image": "http://media.salon.com/2014/06/Screen-Shot-2014-06-11-at-10.43.54-AM.png", "type": "article"}, "twitter": {"description": "Jim Carrey and Jeff Daniels tease the movie as a \"phe-nom-en-on\" VIDEO", "creator": "@prachigu", "image": "http://media.salon.com/2014/06/Screen-Shot-2014-06-11-at-10.43.54-AM.png", "title": "Here is the trailer for \u201cDumb and Dumber To\u201d", "site": "@salon", "card": "summary_large_image"}, "title": "Here is the trailer for \u201cDumb and Dumber To\u201d", "apple-itunes-app": "app-id=549374205, app-argument=http://www.salon.com/", "fb": {"pages": 120680396518, "app_id": 456294607741273}, "keywords": "Salon.com, aol_on, Comedy, Dumb and Dumber, dumb and dumber to, jeff daniels, Jim Carrey, Video", "viewport": "width=device-width, initial-scale=1.0"}, "_id": "\"57477af36914bd0286fcfeb5\"", "article_summary": "Topics: aol_on, Comedy, Dumb and Dumber, dumb and dumber to, jeff daniels, Jim Carrey, Video, Entertainment NewsWatch the \u201cphe-nom-en-on\u201d that is Harry and Lloyd, reunited two decades later for \u201cDumb and Dumber To.\u201d Actors Jim Carrey and Jeff Daniels premiered the trailer for the sequel to their cult comedy classic on \u201cThe Tonight Show\u201d Tuesday night and, yes, the duo is still very dumb.\nBrace yourselves for lots of poop jokes (probably), bad haircuts (definitely), and general raunchiness.\nTurns out that Harry still lives in the same apartment, has a cat named Butthole, but now he has an adult daughter (and Lloyd, not so surprisingly, wants to date her).\nThe movie comes out Nov. 14."}