{"article_title": "Tenants displaced by high-rise fire on Near North Side", "article_keywords": ["displaced", "highrise", "north", "housing", "near", "saidthe", "officials", "tenants", "called", "unit"], "article_url": "http://chicago.suntimes.com/news/tenants-displaced-by-high-rise-fire-on-near-north-side/", "article_text": "Tenants displaced by high-rise fire on Near North Side\n\nThe tenants of a Near North Side high-rise apartment unit were displaced after a fire Saturday afternoon.\n\nCrews were called about 4:20 p.m. to a seond-floor unit in the 14-story building at 1531 N. Clybourn, according to Fire Media Affairs. The high-rise is listed as a public housing property, according to online Chicago Housing Authority records.\n\nAn emergency medical services plan 1 of five ambulances was called as a precaution to the blaze, fire officials said.\n\nThe fire was contained to the unit and consisted mostly of moderate smoke before it was extinguished about 4:45 p.m. No residents or firefighters were injured, officials said.\n\nThe tenants of the unit where the fire started were expected to be displaced until repairs could be made, officials said.\n\nThe cause of the fire was unknown Saturday afternoon.", "article_metadata": {"viewport": "width=device-width", "description": "<p>The tenants of a Near North Side high-rise apartment unit were displaced after a fire Saturday afternoon.</p>", "generator": "WordPress.com", "msapplication-wide310x150logo": "https://s0.wp.com/wp-content/themes/vip/chicagosuntimes/assets/images/favicons/mstile-310x150.png", "twitter": {"url": "http://chicago.suntimes.com/news/tenants-displaced-by-high-rise-fire-on-near-north-side/", "site": "@suntimes", "card": "summary_large_image", "title": "Tenants displaced by high-rise fire on Near North Side"}, "msapplication-TileColor": "#282828", "msapplication-square70x70logo": "https://s0.wp.com/wp-content/themes/vip/chicagosuntimes/assets/images/favicons/mstile-70x70.png", "msapplication-tooltip": "Chicago News, Sports, Politics, Entertainment, Weather and More", "msapplication-square310x310logo": "https://s0.wp.com/wp-content/themes/vip/chicagosuntimes/assets/images/favicons/mstile-310x310.png", "og": {"url": "http://chicago.suntimes.com/news/tenants-displaced-by-high-rise-fire-on-near-north-side/", "site_name": "Chicago Sun-Times", "type": "article", "title": "Tenants displaced by high-rise fire on Near North Side"}, "msapplication-window": "width=device-width;height=device-height", "msapplication-TileImage": "https://s0.wp.com/wp-content/themes/vip/chicagosuntimes/assets/images/favicons/mstile-144x144.png", "application-name": "Chicago Sun-Times", "msapplication-square150x150logo": "https://s0.wp.com/wp-content/themes/vip/chicagosuntimes/assets/images/favicons/mstile-150x150.png", "msapplication-task": "name=Subscribe;action-uri=http://chicago.suntimes.com/feed/;icon-uri=https://s2.wp.com/i/favicon.ico"}, "_id": "\"57477af36914bd0286fcfd3f\"", "article_summary": "Tenants displaced by high-rise fire on Near North SideThe tenants of a Near North Side high-rise apartment unit were displaced after a fire Saturday afternoon.\nThe tenants of the unit where the fire started were expected to be displaced until repairs could be made, officials said.\nThe high-rise is listed as a public housing property, according to online Chicago Housing Authority records.\nAn emergency medical services plan 1 of five ambulances was called as a precaution to the blaze, fire officials said.\nCrews were called about 4:20 p.m. to a seond-floor unit in the 14-story building at 1531 N. Clybourn, according to Fire Media Affairs."}